accesschk2df/Eula.txt
accesschk2df/README.MD
accesschk2df/__init__.py
accesschk2df/accesschk.exe
accesschk2df/accesschk64.exe
accesschk2df/accesschk64a.exe
accesschk2df/requirements.txt
accesschk2df/thirdparty.json
accesschk2df-0.10.dist-info/LICENSE.rst
accesschk2df-0.10.dist-info/METADATA
accesschk2df-0.10.dist-info/WHEEL
accesschk2df-0.10.dist-info/top_level.txt
accesschk2df-0.10.dist-info/RECORD
