Metadata-Version: 2.1
Name: accesschk2df
Version: 0.10
Summary: Automating the retrieval and analysis of access information using accesschk.exe
Home-page: https://github.com/hansalemaos/accesschk2df
Author: Johannes Fischer
Author-email: aulasparticularesdealemaosp@gmail.com
License: MIT
Keywords: accesschk,DataFrame
Classifier: Development Status :: 4 - Beta
Classifier: Programming Language :: Python :: 3 :: Only
Classifier: Programming Language :: Python :: 3.10
Classifier: Topic :: Software Development :: Libraries :: Python Modules
Classifier: Topic :: Utilities
License-File: LICENSE.rst
Requires-Dist: a-pandas-ex-horizontal-explode
Requires-Dist: getfilenuitkapython
Requires-Dist: multisubprocess
Requires-Dist: pandas
